LogOX/__init__.py
LogOX/formatter.py
LogOX/main.py
LogOX-1.0.0b1.dist-info/LICENSE
LogOX-1.0.0b1.dist-info/METADATA
LogOX-1.0.0b1.dist-info/NOTICE
LogOX-1.0.0b1.dist-info/WHEEL
LogOX-1.0.0b1.dist-info/top_level.txt
LogOX-1.0.0b1.dist-info/RECORD
