Metadata-Version: 2.1
Name: LogOX
Version: 1.0.0b1
Summary: My interlayer package for python logging
Home-page: https://github.com/MrEluzium/LogOX
Author: Artem Eluzium
License: Apache License 2.0
Platform: UNKNOWN
Classifier: Development Status :: 4 - Beta
Classifier: Topic :: System :: Logging
Classifier: Programming Language :: Python :: 3
Classifier: Intended Audience :: Developers
Classifier: License :: OSI Approved :: Apache Software License
License-File: LICENSE
License-File: NOTICE
